README.md
setup.py
sensys.egg-info/PKG-INFO
sensys.egg-info/SOURCES.txt
sensys.egg-info/dependency_links.txt
sensys.egg-info/entry_points.txt
sensys.egg-info/requires.txt
sensys.egg-info/top_level.txt
sensys/contrib/__init__.py
sensys/contrib/django/__init__.py
sensys/contrib/django/apps.py
sensys/contrib/django/client.py
sensys/contrib/flask/__init__.py
sensys/plugin/__init__.py
sensys/plugin/core.py
sensys/plugin/errors.py