Metadata-Version: 2.1
Name: sensys
Version: 0.2.0
Summary: Python Sen(try) --> Sys(log) workaround.
Home-page: https://github.com/mu-team/sensys
Author: Kirill (kxnes) Kolesnikov
Author-email: kkxnes@gmail.com
License: The MIT License
Platform: UNKNOWN
Classifier: Programming Language :: Python :: 3.4
Classifier: Programming Language :: Python :: 3.5
Classifier: Programming Language :: Python :: 3.6
Classifier: License :: OSI Approved :: MIT License
Classifier: Operating System :: OS Independent
